hjworks/EntradaPrograma.py
hjworks/PiedraPapelTijeras.py
hjworks/Programa.py
hjworks/TresEnRaya.py
hjworks/Wordle.py
hjworks/__init__.py
hjworks-1.1.3.dist-info/METADATA
hjworks-1.1.3.dist-info/WHEEL
hjworks-1.1.3.dist-info/top_level.txt
hjworks-1.1.3.dist-info/RECORD
